LICENSE.txt
README.md
setup.cfg
setup.py
canopy/__init__.py
canopy/authentication.py
canopy/authentication_data.py
canopy/config_result.py
canopy/constants.py
canopy/create_config.py
canopy/create_list_filter.py
canopy/create_study.py
canopy/defined_kwargs.py
canopy/delete_config.py
canopy/delete_study.py
canopy/dict_to_object.py
canopy/dict_to_object_test.py
canopy/dynamic_dict_to_object.py
canopy/ensure_dict.py
canopy/ensure_sim_type_string.py
canopy/ensure_sim_type_string_test.py
canopy/ensure_study_type_string.py
canopy/ensure_study_type_string_test.py
canopy/find_config.py
canopy/find_study.py
canopy/get_default_config_path.py
canopy/get_study_document.py
canopy/get_study_type_definition_for_sim_version.py
canopy/get_study_type_definition_for_sim_version_test.py
canopy/job_count_to_simulation_count.py
canopy/load_channel.py
canopy/load_config.py
canopy/load_default_config.py
canopy/load_study.py
canopy/load_study_job.py
canopy/load_study_job_scalar_results.py
canopy/load_study_scalar_results.py
canopy/load_vector_metadata.py
canopy/loaded_channel.py
canopy/local_config.py
canopy/not_found_error.py
canopy/process_data_frame.py
canopy/process_data_frame_test.py
canopy/prompt_for_authentication.py
canopy/properties_dict_to_list.py
canopy/proxy_configuration.py
canopy/proxy_configuration_test.py
canopy/request_with_retry.py
canopy/request_with_retry_test.py
canopy/run.py
canopy/serializable_value.py
canopy/session.py
canopy/sim_version_to_number.py
canopy/sim_version_to_number_test.py
canopy/study_job_result.py
canopy/study_result.py
canopy/study_scalar_results.py
canopy/study_types_cache.py
canopy/tenant_sim_version_cache.py
canopy/tenant_users.py
canopy/tenant_users_cache.py
canopy/tenant_users_test.py
canopy/try_load_csv_from_url.py
canopy/units.py
canopy/units_test.py
canopy/update_config.py
canopy/user_settings_cache.py
canopy/wait_for_study.py
canopy.egg-info/PKG-INFO
canopy.egg-info/SOURCES.txt
canopy.egg-info/dependency_links.txt
canopy.egg-info/requires.txt
canopy.egg-info/top_level.txt
canopy/openapi/__init__.py
canopy/openapi/api_client.py
canopy/openapi/configuration.py
canopy/openapi/exceptions.py
