Metadata-Version: 2.1
Name: canopy
Version: 8.66
Summary: Python Client for the Canopy Simulation API
Home-page: https://github.com/canopysimulations/canopy-python/
Author: James Thurley
Author-email: james.thurley@canopysimulations.com
License: MIT
Keywords: Canopy API,Canopy Simulations,Canopy Client
Platform: UNKNOWN
Classifier: Development Status :: 3 - Alpha
Classifier: Intended Audience :: Developers
Classifier: License :: OSI Approved :: MIT License
Classifier: Programming Language :: Python :: 3
Classifier: Programming Language :: Python :: 3.4
Classifier: Programming Language :: Python :: 3.5
Classifier: Programming Language :: Python :: 3.6
